run_fortran/__init__.py
run_fortran/__main__.py
run_fortran-1.0.0.dist-info/LICENSE.md
run_fortran-1.0.0.dist-info/METADATA
run_fortran-1.0.0.dist-info/WHEEL
run_fortran-1.0.0.dist-info/entry_points.txt
run_fortran-1.0.0.dist-info/top_level.txt
run_fortran-1.0.0.dist-info/RECORD
